artefacts_toolkit_rosbag_gpl/__init__.py
artefacts_toolkit_rosbag_gpl/ros2bag2video.py
artefacts_toolkit_rosbag_gpl/version.py
artefacts_toolkit_rosbag_gpl-0.3.3.dist-info/LICENSE
artefacts_toolkit_rosbag_gpl-0.3.3.dist-info/METADATA
artefacts_toolkit_rosbag_gpl-0.3.3.dist-info/WHEEL
artefacts_toolkit_rosbag_gpl-0.3.3.dist-info/top_level.txt
artefacts_toolkit_rosbag_gpl-0.3.3.dist-info/RECORD
