Metadata-Version: 2.2
Name: artefacts_toolkit_rosbag_gpl
Version: 0.3.3
Author-email: FD <fabian@artefacts.com>, AGC <alejandro@artefacts.com>, TN <tomo@artefacts.com>, EP <eric@artefacts.com>
Project-URL: Homepage, https://github.com/art-e-fact/artefacts-toolkit-rosbag_gpl
Project-URL: Bug Tracker, https://github.com/art-e-fact/artefacts-toolkit-rosbag_gpl/issues
Classifier: Programming Language :: Python :: 3
Classifier: License :: OSI Approved :: Apache Software License
Classifier: Operating System :: OS Independent
Requires-Python: >=3.10
License-File: LICENSE
Requires-Dist: opencv-python
Requires-Dist: numpy<2,>=1.26.0
Provides-Extra: dev
Requires-Dist: build; extra == "dev"
Requires-Dist: pyre-check; extra == "dev"
Requires-Dist: pytest; extra == "dev"
Requires-Dist: pytest-cov; extra == "dev"
Requires-Dist: pytest-env; extra == "dev"
Requires-Dist: pytest-mock; extra == "dev"
Requires-Dist: ruff; extra == "dev"
Requires-Dist: setuptools-scm; extra == "dev"
Requires-Dist: twine; extra == "dev"
